eth_account/__init__.py
eth_account/account.py
eth_account/datastructures.py
eth_account/messages.py
eth_account/py.typed
eth_account/_utils/__init__.py
eth_account/_utils/legacy_transactions.py
eth_account/_utils/signing.py
eth_account/_utils/transaction_utils.py
eth_account/_utils/typed_transactions.py
eth_account/_utils/validation.py
eth_account/_utils/structured_data/__init__.py
eth_account/_utils/structured_data/hashing.py
eth_account/_utils/structured_data/validation.py
eth_account/hdaccount/__init__.py
eth_account/hdaccount/_utils.py
eth_account/hdaccount/deterministic.py
eth_account/hdaccount/mnemonic.py
eth_account/hdaccount/wordlist/chinese_simplified.txt
eth_account/hdaccount/wordlist/chinese_traditional.txt
eth_account/hdaccount/wordlist/czech.txt
eth_account/hdaccount/wordlist/english.txt
eth_account/hdaccount/wordlist/french.txt
eth_account/hdaccount/wordlist/italian.txt
eth_account/hdaccount/wordlist/japanese.txt
eth_account/hdaccount/wordlist/korean.txt
eth_account/hdaccount/wordlist/spanish.txt
eth_account/signers/__init__.py
eth_account/signers/base.py
eth_account/signers/local.py
eth_account_ex-0.6.2.dist-info/LICENSE
eth_account_ex-0.6.2.dist-info/METADATA
eth_account_ex-0.6.2.dist-info/WHEEL
eth_account_ex-0.6.2.dist-info/top_level.txt
eth_account_ex-0.6.2.dist-info/RECORD
