Metadata-Version: 2.1
Name: eth-account-ex
Version: 0.6.2
Summary: eth-account: Sign Ethereum transactions and messages with local private keys
Home-page: https://github.com/ethereum/eth-account
Author: The Ethereum Foundation
Author-email: snakecharmers@ethereum.org
License: MIT
Keywords: ethereum
Classifier: Development Status :: 3 - Alpha
Classifier: Intended Audience :: Developers
Classifier: License :: OSI Approved :: MIT License
Classifier: Natural Language :: English
Classifier: Operating System :: MacOS
Classifier: Operating System :: POSIX
Classifier: Programming Language :: Python :: 3
Classifier: Programming Language :: Python :: 3.7
Classifier: Programming Language :: Python :: 3.8
Classifier: Programming Language :: Python :: 3.9
Classifier: Programming Language :: Python :: 3.10
Requires-Python: >=3.6, <4
License-File: LICENSE
Requires-Dist: bitarray (<3,>=2.4.0)
Requires-Dist: eth-abi (<4,>=3.0.0)
Requires-Dist: eth-keyfile (<0.7.0,>=0.6.0)
Requires-Dist: eth-keys (<0.5,>=0.4.0)
Requires-Dist: eth-rlp (<1,>=0.3.0)
Requires-Dist: eth-utils (<3,>=2.0.0)
Requires-Dist: hexbytes (<1,>=0.1.0)
Requires-Dist: rlp (<4,>=1.0.0)
Provides-Extra: dev
Requires-Dist: bumpversion (<1,>=0.5.3) ; extra == 'dev'
Requires-Dist: pytest-watch (<5,>=4.1.0) ; extra == 'dev'
Requires-Dist: wheel ; extra == 'dev'
Requires-Dist: twine ; extra == 'dev'
Requires-Dist: ipython ; extra == 'dev'
Requires-Dist: hypothesis (<5,>=4.18.0) ; extra == 'dev'
Requires-Dist: pytest (<7,>=6.2.5) ; extra == 'dev'
Requires-Dist: pytest-xdist ; extra == 'dev'
Requires-Dist: tox (==3.25.0) ; extra == 'dev'
Requires-Dist: flake8 (==3.7.9) ; extra == 'dev'
Requires-Dist: isort (<5,>=4.2.15) ; extra == 'dev'
Requires-Dist: mypy (==0.910) ; extra == 'dev'
Requires-Dist: pydocstyle (<6,>=5.0.0) ; extra == 'dev'
Requires-Dist: Sphinx (<5,>=1.6.5) ; extra == 'dev'
Requires-Dist: jinja2 (<3.1.0,>=3.0.0) ; extra == 'dev'
Requires-Dist: sphinx-rtd-theme (<1,>=0.1.9) ; extra == 'dev'
Requires-Dist: towncrier (==18.5.0) ; extra == 'dev'
Provides-Extra: doc
Requires-Dist: Sphinx (<5,>=1.6.5) ; extra == 'doc'
Requires-Dist: jinja2 (<3.1.0,>=3.0.0) ; extra == 'doc'
Requires-Dist: sphinx-rtd-theme (<1,>=0.1.9) ; extra == 'doc'
Requires-Dist: towncrier (==18.5.0) ; extra == 'doc'
Provides-Extra: lint
Requires-Dist: flake8 (==3.7.9) ; extra == 'lint'
Requires-Dist: isort (<5,>=4.2.15) ; extra == 'lint'
Requires-Dist: mypy (==0.910) ; extra == 'lint'
Requires-Dist: pydocstyle (<6,>=5.0.0) ; extra == 'lint'
Provides-Extra: test
Requires-Dist: hypothesis (<5,>=4.18.0) ; extra == 'test'
Requires-Dist: pytest (<7,>=6.2.5) ; extra == 'test'
Requires-Dist: pytest-xdist ; extra == 'test'
Requires-Dist: tox (==3.25.0) ; extra == 'test'
